llama_index/node_parser/slide/__init__.py
llama_index/node_parser/slide/base.py
llama_index_node_parser_slide-0.2.1.dist-info/METADATA
llama_index_node_parser_slide-0.2.1.dist-info/WHEEL
llama_index_node_parser_slide-0.2.1.dist-info/licenses/LICENSE
llama_index_node_parser_slide-0.2.1.dist-info/RECORD
