Metadata-Version: 2.4
Name: llama-index-node-parser-slide
Version: 0.2.1
Summary: llama-index node_parser slide node parser integration
Author-email: Anish Joshi <anish.yog10@gmail.com>
License-Expression: MIT
License-File: LICENSE
Requires-Python: <4.0,>=3.9
Requires-Dist: llama-index-core<0.15,>=0.13.0
